pyzx7/__init__.py
pyzx7/zx7.cpython-37m-darwin.so
pyzx7-0.0.3.dist-info/LICENSE
pyzx7-0.0.3.dist-info/METADATA
pyzx7-0.0.3.dist-info/WHEEL
pyzx7-0.0.3.dist-info/top_level.txt
pyzx7-0.0.3.dist-info/RECORD
