Metadata-Version: 2.1
Name: pyzx7
Version: 0.0.3
Summary: ZX7 library Python integration
Home-page: https://github.com/jsmolina/pyzx7
Author: jsmolina
License: UNKNOWN
Platform: UNKNOWN
